dt_python_sdk-1.1.1.dist-info/METADATA
dt_python_sdk-1.1.1.dist-info/WHEEL
dt_python_sdk/__init__.py
dt_python_sdk/datatowerai_sdk.py
dt_python_sdk/dt_core_base_py.abi3.so
dt_python_sdk-1.1.1.dist-info/RECORD
