Metadata-Version: 2.4
Name: dt-python-sdk
Version: 1.1.1
Classifier: Programming Language :: Rust
Classifier: Programming Language :: Python :: Implementation :: CPython
Classifier: Programming Language :: Python :: Implementation :: PyPy
Summary: DataTower.ai Core SDK for Python
Author: DataTower.ai
Requires-Python: >=3.7
Project-URL: Homepage, https://datatower.ai/
